rdoclient/__init__.py
rdoclient/rdoclient.py
rdoclient-1.5.0.dist-info/LICENSE
rdoclient-1.5.0.dist-info/METADATA
rdoclient-1.5.0.dist-info/WHEEL
rdoclient-1.5.0.dist-info/top_level.txt
rdoclient-1.5.0.dist-info/RECORD
