Metadata-Version: 2.1
Name: rdoclient
Version: 1.5.0
Summary: The official RANDOM.ORG JSON-RPC API (Release 4) implementation for Python 2 and 3.
Home-page: https://www.random.org/
Author: RANDOM.ORG
Author-email: contact@random.org
License: MIT
Project-URL: Documentation, https://api.random.org/json-rpc/4
Project-URL: Source Code, https://github.com/RandomOrg/JSON-RPC-Python
Keywords: RANDOM.ORG random client implementation
Classifier: Development Status :: 4 - Beta
Classifier: Intended Audience :: Developers
Classifier: License :: OSI Approved :: MIT License
Classifier: Programming Language :: Python :: 2.7
Classifier: Programming Language :: Python :: 3.5
Classifier: Programming Language :: Python :: 3.6
Classifier: Programming Language :: Python :: 3.7
Classifier: Programming Language :: Python :: 3.8
Classifier: Programming Language :: Python :: 3.9
Classifier: Programming Language :: Python :: 3.10
Classifier: Programming Language :: Python :: 3.11
Classifier: Topic :: Software Development :: Libraries :: Python Modules
Requires-Python: >=2.7, !=3.0.*, !=3.1.*, !=3.2.*, !=3.3.*, !=3.4.*
License-File: LICENSE
Requires-Dist: requests
Requires-Dist: six
